Workbook

Sheet Employees
A1: Employee_ID | B1: First_Name | C1: Last_Name | D1: Email | E1: Location | F1: Department | G1: Role | H1: Join_Date | I1: Base_Salary
A2: EMP1000 | B2: Priya | C2: Miller | D2: priya.miller@company.com | E2: New York, NY | F2: Finance | G2: Director | H2: 2019-06-04 | I2: 217394
A3: EMP1001 | B3: Jane | C3: Anderson | D3: jane.anderson@company.com | E3: Mumbai, IN | F3: Data Science | G3: Manager | H3: 2022-01-08 | I3: 155781
A4: EMP1002 | B4: Sarah | C4: Garcia | D4: sarah.garcia@company.com | E4: Austin, TX | F4: HR | G4: Director | H4: 2018-02-11 | I4: 228977
A5: EMP1003 | B5: Carlos | C5: Sharma | D5: carlos.sharma@company.com | E5: San Francisco, CA | F5: Sales | G5: Senior | H5: 2018-10-03 | I5: 86350
A6: EMP1004 | B6: David | C6: Miller | D6: david.miller@company.com | E6: Mumbai, IN | F6: Finance | G6: Lead | H6: 2020-02-19 | I6: 122767
A7: EMP1005 | B7: Daniel | C7: Davis | D7: daniel.davis@company.com | E7: San Francisco, CA | F7: Finance | G7: Lead | H7: 2019-03-09 | I7: 107479
A8: EMP1006 | B8: Emma | C8: Johnson | D8: emma.johnson@company.com | E8: Remote | F8: Finance | G8: Junior | H8: 2023-04-01 | I8: 60137
A9: EMP1007 | B9: Sneha | C9: Smith | D9: sneha.smith@company.com | E9: Austin, TX | F9: Data Science | G9: Director | H9: 2021-11-07 | I9: 247315
A10: EMP1008 | B10: Chris | C10: Taylor | D10: chris.taylor@company.com | E10: Remote | F10: Sales | G10: Junior | H10: 2019-05-28 | I10: 59428
A11: EMP1009 | B11: Daniel | C11: Lee | D11: daniel.lee@company.com | E11: Mumbai, IN | F11: Finance | G11: Junior | H11: 2019-08-07 | I11: 53660
A12: EMP1010 | B12: Emma | C12: Lee | D12: emma.lee@company.com | E12: San Francisco, CA | F12: HR | G12: Junior | H12: 2019-02-08 | I12: 50341
A13: EMP1011 | B13: Laura | C13: Garcia | D13: laura.garcia@company.com | E13: London, UK | F13: Engineering | G13: Senior | H13: 2023-02-18 | I13: 95200
... A251: EMP1249 | B251: Priya | C251: Smith | D251: priya.smith@company.com | E251: Austin, TX | F251: Data Science | G251: Manager | H251: 2021-05-22 | I251: 153990

Sheet Benefits
A1: Role | B1: Health_Ins_Cost | C1: PF_Percentage
A2: Junior | B2: 150 | C2: 0.05
A3: Senior | B3: 250 | C3: 0.08
A4: Lead | B4: 350 | C4: 0.1
A5: Manager | B5: 500 | C5: 0.12
A6: Director | B6: 800 | C6: 0.15

Sheet Tax_Brackets
A1: Min_Income | B1: Max_Income | C1: Base_Tax | D1: Marginal_Rate
A2: 0 | B2: 44724 | C2: 0 | D2: 0.12
A3: 44725 | B3: 95374 | C3: 5143 | D3: 0.22
A4: 95375 | B4: 182099 | C4: 16290 | D4: 0.24
A5: 182100 | B5: 231249 | C5: 37104 | D5: 0.32
A6: 231250 | B6: 9999999 | C6: 48898 | D6: 0.35

Sheet Payroll_Run
A1: Employee_ID | B1: Perf_Score | C1: OT_Hours | D1: Role_F | E1: Base_Salary_F | F1: Gross_Salary_F | G1: Health_Deduct_F | H1: Tax_Rate_F | I1: Net_Salary_F
A2: EMP1000 | B2: 4.1 | C2: 0 | D2: =VLOOKUP(A2, Employees!A:I, 7, FALSE) -> 0 | E2: =VLOOKUP(A2, Employees!A:I, 9, FALSE) -> 0 | F2: =E2 + (E2*(B2/5)*0.1) + (C2*45) -> 0 | G2: =VLOOKUP(D2, Benefits!A:C, 2, FALSE) -> 0 | H2: =VLOOKUP(F2, Tax_Brackets!A:D, 4, TRUE) -> 0 | I2: =F2 - G2 - (F2 * H2) -> 0
A3: EMP1001 | B3: 3.2 | C3: 0 | D3: =VLOOKUP(A3, Employees!A:I, 7, FALSE) -> 0 | E3: =VLOOKUP(A3, Employees!A:I, 9, FALSE) -> 0 | F3: =E3 + (E3*(B3/5)*0.1) + (C3*45) -> 0 | G3: =VLOOKUP(D3, Benefits!A:C, 2, FALSE) -> 0 | H3: =VLOOKUP(F3, Tax_Brackets!A:D, 4, TRUE) -> 0 | I3: =F3 - G3 - (F3 * H3) -> 0
A4: EMP1002 | B4: 3.7 | C4: 0 | D4: =VLOOKUP(A4, Employees!A:I, 7, FALSE) -> 0 | E4: =VLOOKUP(A4, Employees!A:I, 9, FALSE) -> 0 | F4: =E4 + (E4*(B4/5)*0.1) + (C4*45) -> 0 | G4: =VLOOKUP(D4, Benefits!A:C, 2, FALSE) -> 0 | H4: =VLOOKUP(F4, Tax_Brackets!A:D, 4, TRUE) -> 0 | I4: =F4 - G4 - (F4 * H4) -> 0
A5: EMP1003 | B5: 2.9 | C5: 0 | D5: =VLOOKUP(A5, Employees!A:I, 7, FALSE) -> 0 | E5: =VLOOKUP(A5, Employees!A:I, 9, FALSE) -> 0 | F5: =E5 + (E5*(B5/5)*0.1) + (C5*45) -> 0 | G5: =VLOOKUP(D5, Benefits!A:C, 2, FALSE) -> 0 | H5: =VLOOKUP(F5, Tax_Brackets!A:D, 4, TRUE) -> 0 | I5: =F5 - G5 - (F5 * H5) -> 0
A6: EMP1004 | B6: 2 | C6: 0 | D6: =VLOOKUP(A6, Employees!A:I, 7, FALSE) -> 0 | E6: =VLOOKUP(A6, Employees!A:I, 9, FALSE) -> 0 | F6: =E6 + (E6*(B6/5)*0.1) + (C6*45) -> 0 | G6: =VLOOKUP(D6, Benefits!A:C, 2, FALSE) -> 0 | H6: =VLOOKUP(F6, Tax_Brackets!A:D, 4, TRUE) -> 0 | I6: =F6 - G6 - (F6 * H6) -> 0
A7: EMP1005 | B7: 4.6 | C7: 0 | D7: =VLOOKUP(A7, Employees!A:I, 7, FALSE) -> 0 | E7: =VLOOKUP(A7, Employees!A:I, 9, FALSE) -> 0 | F7: =E7 + (E7*(B7/5)*0.1) + (C7*45) -> 0 | G7: =VLOOKUP(D7, Benefits!A:C, 2, FALSE) -> 0 | H7: =VLOOKUP(F7, Tax_Brackets!A:D, 4, TRUE) -> 0 | I7: =F7 - G7 - (F7 * H7) -> 0
A8: EMP1006 | B8: 4.3 | C8: 11 | D8: =VLOOKUP(A8, Employees!A:I, 7, FALSE) -> 0 | E8: =VLOOKUP(A8, Employees!A:I, 9, FALSE) -> 0 | F8: =E8 + (E8*(B8/5)*0.1) + (C8*45) -> 0 | G8: =VLOOKUP(D8, Benefits!A:C, 2, FALSE) -> 0 | H8: =VLOOKUP(F8, Tax_Brackets!A:D, 4, TRUE) -> 0 | I8: =F8 - G8 - (F8 * H8) -> 0
A9: EMP1007 | B9: 3.6 | C9: 0 | D9: =VLOOKUP(A9, Employees!A:I, 7, FALSE) -> 0 | E9: =VLOOKUP(A9, Employees!A:I, 9, FALSE) -> 0 | F9: =E9 + (E9*(B9/5)*0.1) + (C9*45) -> 0 | G9: =VLOOKUP(D9, Benefits!A:C, 2, FALSE) -> 0 | H9: =VLOOKUP(F9, Tax_Brackets!A:D, 4, TRUE) -> 0 | I9: =F9 - G9 - (F9 * H9) -> 0
A10: EMP1008 | B10: 3.8 | C10: 11 | D10: =VLOOKUP(A10, Employees!A:I, 7, FALSE) -> 0 | E10: =VLOOKUP(A10, Employees!A:I, 9, FALSE) -> 0 | F10: =E10 + (E10*(B10/5)*0.1) + (C10*45) -> 0 | G10: =VLOOKUP(D10, Benefits!A:C, 2, FALSE) -> 0 | H10: =VLOOKUP(F10, Tax_Brackets!A:D, 4, TRUE) -> 0 | I10: =F10 - G10 - (F10 * H10) -> 0
A11: EMP1009 | B11: 3.1 | C11: 5 | D11: =VLOOKUP(A11, Employees!A:I, 7, FALSE) -> 0 | E11: =VLOOKUP(A11, Employees!A:I, 9, FALSE) -> 0 | F11: =E11 + (E11*(B11/5)*0.1) + (C11*45) -> 0 | G11: =VLOOKUP(D11, Benefits!A:C, 2, FALSE) -> 0 | H11: =VLOOKUP(F11, Tax_Brackets!A:D, 4, TRUE) -> 0 | I11: =F11 - G11 - (F11 * H11) -> 0
A12: EMP1010 | B12: 4.9 | C12: 10 | D12: =VLOOKUP(A12, Employees!A:I, 7, FALSE) -> 0 | E12: =VLOOKUP(A12, Employees!A:I, 9, FALSE) -> 0 | F12: =E12 + (E12*(B12/5)*0.1) + (C12*45) -> 0 | G12: =VLOOKUP(D12, Benefits!A:C, 2, FALSE) -> 0 | H12: =VLOOKUP(F12, Tax_Brackets!A:D, 4, TRUE) -> 0 | I12: =F12 - G12 - (F12 * H12) -> 0
A13: EMP1011 | B13: 3.6 | C13: 9 | D13: =VLOOKUP(A13, Employees!A:I, 7, FALSE) -> 0 | E13: =VLOOKUP(A13, Employees!A:I, 9, FALSE) -> 0 | F13: =E13 + (E13*(B13/5)*0.1) + (C13*45) -> 0 | G13: =VLOOKUP(D13, Benefits!A:C, 2, FALSE) -> 0 | H13: =VLOOKUP(F13, Tax_Brackets!A:D, 4, TRUE) -> 0 | I13: =F13 - G13 - (F13 * H13) -> 0
... A251: EMP1249 | B251: 4.3 | C251: 0 | D251: =VLOOKUP(A251, Employees!A:I, 7, FALSE) -> 0 | E251: =VLOOKUP(A251, Employees!A:I, 9, FALSE) -> 0 | F251: =E251 + (E251*(B251/5)*0.1) + (C251*45) -> 0 | G251: =VLOOKUP(D251, Benefits!A:C, 2, FALSE) -> 0 | H251: =VLOOKUP(F251, Tax_Brackets!A:D, 4, TRUE) -> 0 | I251: =F251 - G251 - (F251 * H251) -> 0
