Workbook

Sheet Products
A1: Product_ID | B1: Product_Name | C1: Category | D1: COGS | E1: Retail_Price | F1: Weight_kg
A2: PRD-100 | B2: Furniture Item 1 | C2: Furniture | D2: 444 | E2: 888 | F2: 30.8
A3: PRD-101 | B3: Apparel Item 2 | C3: Apparel | D3: 7 | E3: 21 | F3: 0.54
A4: PRD-102 | B4: Home Goods Item 3 | C4: Home Goods | D4: 84 | E4: 210 | F4: 1.56
A5: PRD-103 | B5: Electronics Item 4 | C5: Electronics | D5: 62 | E5: 86.8 | F5: 2.39
A6: PRD-104 | B6: Fitness Item 5 | C6: Fitness | D6: 179 | E6: 322.2 | F6: 18.34
A7: PRD-105 | B7: Electronics Item 6 | C7: Electronics | D7: 271 | E7: 379.4 | F7: 2.78
A8: PRD-106 | B8: Fitness Item 7 | C8: Fitness | D8: 142 | E8: 255.6 | F8: 6.48
A9: PRD-107 | B9: Apparel Item 8 | C9: Apparel | D9: 5 | E9: 15 | F9: 0.25
A10: PRD-108 | B10: Electronics Item 9 | C10: Electronics | D10: 172 | E10: 240.8 | F10: 1.84
A11: PRD-109 | B11: Fitness Item 10 | C11: Fitness | D11: 156 | E11: 280.8 | F11: 10.36
A12: PRD-110 | B12: Fitness Item 11 | C12: Fitness | D12: 54 | E12: 97.2 | F12: 11.98
A13: PRD-111 | B13: Fitness Item 12 | C13: Fitness | D13: 123 | E13: 221.4 | F13: 24.32
... A51: PRD-149 | B51: Fitness Item 50 | C51: Fitness | D51: 51 | E51: 91.8 | F51: 18.32

Sheet Shipping_Zones
A1: Zone_Code | B1: Flat_Fee | C1: Cost_Per_Kg
A2: Zone_A_Local | B2: 5 | C2: 0.5
A3: Zone_B_Regional | B3: 12.5 | C3: 1.25
A4: Zone_C_National | B4: 25 | C4: 2.5
A5: Zone_D_Remote | B5: 50 | C5: 5

Sheet Volume_Discounts
A1: Min_Qty | B1: Max_Qty | C1: Discount_Pct
A2: 0 | B2: 9 | C2: 0
A3: 10 | B3: 24 | C3: 0.05
A4: 25 | B4: 49 | C4: 0.1
A5: 50 | B5: 99 | C5: 0.15
A6: 100 | B6: 9999 | C6: 0.25

Sheet Sales_Ledger
A1: Order_ID | B1: Order_Date | C1: Product_ID | D1: Quantity | E1: Zone_Code | F1: COGS_F | G1: Retail_Price_F | H1: Unit_Weight_F | I1: Gross_Rev_F | J1: Discount_Pct_F | K1: Net_Rev_F | L1: Total_Weight_F | M1: Ship_Flat_F | N1: Ship_Per_Kg_F | O1: Total_Shipping_F | P1: Total_Cost_F | Q1: Net_Profit_F
A2: ORD-10000 | B2: 2023-01-24 | C2: PRD-141 | D2: 8 | E2: Zone_B_Regional | F2: =VLOOKUP(C2, Products!A:F, 4, FALSE) -> 0 | G2: =VLOOKUP(C2, Products!A:F, 5, FALSE) -> 0 | H2: =VLOOKUP(C2, Products!A:F, 6, FALSE) -> 0 | I2: =G2 * D2 -> 0 | J2: =VLOOKUP(D2, Volume_Discounts!A:C, 3, TRUE) -> 0 | K2: =I2 * (1 - J2) -> 0 | L2: =H2 * D2 -> 0 | M2: =VLOOKUP(E2, Shipping_Zones!A:C, 2, FALSE) -> 0 | N2: =VLOOKUP(E2, Shipping_Zones!A:C, 3, FALSE) -> 0 | O2: =M2 + (N2 * L2) -> 0 | P2: =(F2 * D2) + O2 -> 0 | Q2: =K2 - P2 -> 0
A3: ORD-10001 | B3: 2023-05-15 | C3: PRD-143 | D3: 110 | E3: Zone_B_Regional | F3: =VLOOKUP(C3, Products!A:F, 4, FALSE) -> 0 | G3: =VLOOKUP(C3, Products!A:F, 5, FALSE) -> 0 | H3: =VLOOKUP(C3, Products!A:F, 6, FALSE) -> 0 | I3: =G3 * D3 -> 0 | J3: =VLOOKUP(D3, Volume_Discounts!A:C, 3, TRUE) -> 0 | K3: =I3 * (1 - J3) -> 0 | L3: =H3 * D3 -> 0 | M3: =VLOOKUP(E3, Shipping_Zones!A:C, 2, FALSE) -> 0 | N3: =VLOOKUP(E3, Shipping_Zones!A:C, 3, FALSE) -> 0 | O3: =M3 + (N3 * L3) -> 0 | P3: =(F3 * D3) + O3 -> 0 | Q3: =K3 - P3 -> 0
A4: ORD-10002 | B4: 2023-05-01 | C4: PRD-145 | D4: 62 | E4: Zone_B_Regional | F4: =VLOOKUP(C4, Products!A:F, 4, FALSE) -> 0 | G4: =VLOOKUP(C4, Products!A:F, 5, FALSE) -> 0 | H4: =VLOOKUP(C4, Products!A:F, 6, FALSE) -> 0 | I4: =G4 * D4 -> 0 | J4: =VLOOKUP(D4, Volume_Discounts!A:C, 3, TRUE) -> 0 | K4: =I4 * (1 - J4) -> 0 | L4: =H4 * D4 -> 0 | M4: =VLOOKUP(E4, Shipping_Zones!A:C, 2, FALSE) -> 0 | N4: =VLOOKUP(E4, Shipping_Zones!A:C, 3, FALSE) -> 0 | O4: =M4 + (N4 * L4) -> 0 | P4: =(F4 * D4) + O4 -> 0 | Q4: =K4 - P4 -> 0
A5: ORD-10003 | B5: 2023-03-21 | C5: PRD-140 | D5: 12 | E5: Zone_C_National | F5: =VLOOKUP(C5, Products!A:F, 4, FALSE) -> 0 | G5: =VLOOKUP(C5, Products!A:F, 5, FALSE) -> 0 | H5: =VLOOKUP(C5, Products!A:F, 6, FALSE) -> 0 | I5: =G5 * D5 -> 0 | J5: =VLOOKUP(D5, Volume_Discounts!A:C, 3, TRUE) -> 0 | K5: =I5 * (1 - J5) -> 0 | L5: =H5 * D5 -> 0 | M5: =VLOOKUP(E5, Shipping_Zones!A:C, 2, FALSE) -> 0 | N5: =VLOOKUP(E5, Shipping_Zones!A:C, 3, FALSE) -> 0 | O5: =M5 + (N5 * L5) -> 0 | P5: =(F5 * D5) + O5 -> 0 | Q5: =K5 - P5 -> 0
A6: ORD-10004 | B6: 2023-08-10 | C6: PRD-129 | D6: 54 | E6: Zone_D_Remote | F6: =VLOOKUP(C6, Products!A:F, 4, FALSE) -> 0 | G6: =VLOOKUP(C6, Products!A:F, 5, FALSE) -> 0 | H6: =VLOOKUP(C6, Products!A:F, 6, FALSE) -> 0 | I6: =G6 * D6 -> 0 | J6: =VLOOKUP(D6, Volume_Discounts!A:C, 3, TRUE) -> 0 | K6: =I6 * (1 - J6) -> 0 | L6: =H6 * D6 -> 0 | M6: =VLOOKUP(E6, Shipping_Zones!A:C, 2, FALSE) -> 0 | N6: =VLOOKUP(E6, Shipping_Zones!A:C, 3, FALSE) -> 0 | O6: =M6 + (N6 * L6) -> 0 | P6: =(F6 * D6) + O6 -> 0 | Q6: =K6 - P6 -> 0
A7: ORD-10005 | B7: 2023-10-13 | C7: PRD-120 | D7: 8 | E7: Zone_A_Local | F7: =VLOOKUP(C7, Products!A:F, 4, FALSE) -> 0 | G7: =VLOOKUP(C7, Products!A:F, 5, FALSE) -> 0 | H7: =VLOOKUP(C7, Products!A:F, 6, FALSE) -> 0 | I7: =G7 * D7 -> 0 | J7: =VLOOKUP(D7, Volume_Discounts!A:C, 3, TRUE) -> 0 | K7: =I7 * (1 - J7) -> 0 | L7: =H7 * D7 -> 0 | M7: =VLOOKUP(E7, Shipping_Zones!A:C, 2, FALSE) -> 0 | N7: =VLOOKUP(E7, Shipping_Zones!A:C, 3, FALSE) -> 0 | O7: =M7 + (N7 * L7) -> 0 | P7: =(F7 * D7) + O7 -> 0 | Q7: =K7 - P7 -> 0
A8: ORD-10006 | B8: 2023-07-03 | C8: PRD-127 | D8: 101 | E8: Zone_C_National | F8: =VLOOKUP(C8, Products!A:F, 4, FALSE) -> 0 | G8: =VLOOKUP(C8, Products!A:F, 5, FALSE) -> 0 | H8: =VLOOKUP(C8, Products!A:F, 6, FALSE) -> 0 | I8: =G8 * D8 -> 0 | J8: =VLOOKUP(D8, Volume_Discounts!A:C, 3, TRUE) -> 0 | K8: =I8 * (1 - J8) -> 0 | L8: =H8 * D8 -> 0 | M8: =VLOOKUP(E8, Shipping_Zones!A:C, 2, FALSE) -> 0 | N8: =VLOOKUP(E8, Shipping_Zones!A:C, 3, FALSE) -> 0 | O8: =M8 + (N8 * L8) -> 0 | P8: =(F8 * D8) + O8 -> 0 | Q8: =K8 - P8 -> 0
A9: ORD-10007 | B9: 2023-12-19 | C9: PRD-134 | D9: 75 | E9: Zone_B_Regional | F9: =VLOOKUP(C9, Products!A:F, 4, FALSE) -> 0 | G9: =VLOOKUP(C9, Products!A:F, 5, FALSE) -> 0 | H9: =VLOOKUP(C9, Products!A:F, 6, FALSE) -> 0 | I9: =G9 * D9 -> 0 | J9: =VLOOKUP(D9, Volume_Discounts!A:C, 3, TRUE) -> 0 | K9: =I9 * (1 - J9) -> 0 | L9: =H9 * D9 -> 0 | M9: =VLOOKUP(E9, Shipping_Zones!A:C, 2, FALSE) -> 0 | N9: =VLOOKUP(E9, Shipping_Zones!A:C, 3, FALSE) -> 0 | O9: =M9 + (N9 * L9) -> 0 | P9: =(F9 * D9) + O9 -> 0 | Q9: =K9 - P9 -> 0
A10: ORD-10008 | B10: 2023-03-04 | C10: PRD-127 | D10: 105 | E10: Zone_A_Local | F10: =VLOOKUP(C10, Products!A:F, 4, FALSE) -> 0 | G10: =VLOOKUP(C10, Products!A:F, 5, FALSE) -> 0 | H10: =VLOOKUP(C10, Products!A:F, 6, FALSE) -> 0 | I10: =G10 * D10 -> 0 | J10: =VLOOKUP(D10, Volume_Discounts!A:C, 3, TRUE) -> 0 | K10: =I10 * (1 - J10) -> 0 | L10: =H10 * D10 -> 0 | M10: =VLOOKUP(E10, Shipping_Zones!A:C, 2, FALSE) -> 0 | N10: =VLOOKUP(E10, Shipping_Zones!A:C, 3, FALSE) -> 0 | O10: =M10 + (N10 * L10) -> 0 | P10: =(F10 * D10) + O10 -> 0 | Q10: =K10 - P10 -> 0
A11: ORD-10009 | B11: 2023-03-03 | C11: PRD-144 | D11: 58 | E11: Zone_C_National | F11: =VLOOKUP(C11, Products!A:F, 4, FALSE) -> 0 | G11: =VLOOKUP(C11, Products!A:F, 5, FALSE) -> 0 | H11: =VLOOKUP(C11, Products!A:F, 6, FALSE) -> 0 | I11: =G11 * D11 -> 0 | J11: =VLOOKUP(D11, Volume_Discounts!A:C, 3, TRUE) -> 0 | K11: =I11 * (1 - J11) -> 0 | L11: =H11 * D11 -> 0 | M11: =VLOOKUP(E11, Shipping_Zones!A:C, 2, FALSE) -> 0 | N11: =VLOOKUP(E11, Shipping_Zones!A:C, 3, FALSE) -> 0 | O11: =M11 + (N11 * L11) -> 0 | P11: =(F11 * D11) + O11 -> 0 | Q11: =K11 - P11 -> 0
A12: ORD-10010 | B12: 2023-10-24 | C12: PRD-118 | D12: 109 | E12: Zone_A_Local | F12: =VLOOKUP(C12, Products!A:F, 4, FALSE) -> 0 | G12: =VLOOKUP(C12, Products!A:F, 5, FALSE) -> 0 | H12: =VLOOKUP(C12, Products!A:F, 6, FALSE) -> 0 | I12: =G12 * D12 -> 0 | J12: =VLOOKUP(D12, Volume_Discounts!A:C, 3, TRUE) -> 0 | K12: =I12 * (1 - J12) -> 0 | L12: =H12 * D12 -> 0 | M12: =VLOOKUP(E12, Shipping_Zones!A:C, 2, FALSE) -> 0 | N12: =VLOOKUP(E12, Shipping_Zones!A:C, 3, FALSE) -> 0 | O12: =M12 + (N12 * L12) -> 0 | P12: =(F12 * D12) + O12 -> 0 | Q12: =K12 - P12 -> 0
A13: ORD-10011 | B13: 2023-03-29 | C13: PRD-138 | D13: 7 | E13: Zone_D_Remote | F13: =VLOOKUP(C13, Products!A:F, 4, FALSE) -> 0 | G13: =VLOOKUP(C13, Products!A:F, 5, FALSE) -> 0 | H13: =VLOOKUP(C13, Products!A:F, 6, FALSE) -> 0 | I13: =G13 * D13 -> 0 | J13: =VLOOKUP(D13, Volume_Discounts!A:C, 3, TRUE) -> 0 | K13: =I13 * (1 - J13) -> 0 | L13: =H13 * D13 -> 0 | M13: =VLOOKUP(E13, Shipping_Zones!A:C, 2, FALSE) -> 0 | N13: =VLOOKUP(E13, Shipping_Zones!A:C, 3, FALSE) -> 0 | O13: =M13 + (N13 * L13) -> 0 | P13: =(F13 * D13) + O13 -> 0 | Q13: =K13 - P13 -> 0
... A301: ORD-10299 | B301: 2023-09-24 | C301: PRD-140 | D301: 106 | E301: Zone_B_Regional | F301: =VLOOKUP(C301, Products!A:F, 4, FALSE) -> 0 | G301: =VLOOKUP(C301, Products!A:F, 5, FALSE) -> 0 | H301: =VLOOKUP(C301, Products!A:F, 6, FALSE) -> 0 | I301: =G301 * D301 -> 0 | J301: =VLOOKUP(D301, Volume_Discounts!A:C, 3, TRUE) -> 0 | K301: =I301 * (1 - J301) -> 0 | L301: =H301 * D301 -> 0 | M301: =VLOOKUP(E301, Shipping_Zones!A:C, 2, FALSE) -> 0 | N301: =VLOOKUP(E301, Shipping_Zones!A:C, 3, FALSE) -> 0 | O301: =M301 + (N301 * L301) -> 0 | P301: =(F301 * D301) + O301 -> 0 | Q301: =K301 - P301 -> 0
